ezq_driver/__init__.py
ezq_driver/constant.py
ezq_driver/driver.py
ezq_driver/logger.py
ezq_driver/utils.py
ezq_driver/version.py
ezq_driver/error/__init__.py
ezq_driver/error/awg_error.py
ezq_driver/error/comm_error.py
ezq_driver/error/daq_error.py
ezq_driver/error/hardware_error.py
ezq_driver/error/mix_error.py
ezq_driver/protocol/__init__.py
ezq_driver/protocol/cmu_protocol.py
ezq_driver/protocol/data_analysis.py
ezq_driver/protocol/pipeline_instruction.py
ezq_driver/register/__init__.py
ezq_driver/register/awg_register.py
ezq_driver/register/cmu_register.py
ezq_driver/register/daq_register.py
ezq_driver/register/mix_register.py
ezq_driver/units/__init__.py
ezq_driver/units/awg_unit.py
ezq_driver/units/cmu_unit.py
ezq_driver/units/daq_unit.py
ezq_driver/units/mix_unit.py
ezq_driver-2.4.2.dist-info/LICENSE
ezq_driver-2.4.2.dist-info/METADATA
ezq_driver-2.4.2.dist-info/WHEEL
ezq_driver-2.4.2.dist-info/top_level.txt
ezq_driver-2.4.2.dist-info/zip-safe
ezq_driver-2.4.2.dist-info/RECORD
