Metadata-Version: 2.1
Name: ezq-driver
Version: 2.4.2
Summary: ez-Q 2.0 engine device control module
Home-page: http://10.99.7.132:9090/EZQ2.0-DRIVER/ezq2_driver.git
Author: wangliangyuan
Author-email: wangleungy@ustc.edu.cn
License: UNKNOWN
Platform: UNKNOWN
